kupy/__init__.py
kupy/base.py
kupy/config.py
kupy/dbadaptor.py
kupy/logger.py
kupy-0.1.14.dist-info/LICENSE
kupy-0.1.14.dist-info/METADATA
kupy-0.1.14.dist-info/WHEEL
kupy-0.1.14.dist-info/entry_points.txt
kupy-0.1.14.dist-info/top_level.txt
kupy-0.1.14.dist-info/RECORD
