Metadata-Version: 2.1
Name: kupy
Version: 0.1.14
Summary: Awesome kupy created by ryanzhang
Home-page: https://github.com/ryanzhang/kupy/
Author: ryanzhang
License: UNKNOWN
Platform: UNKNOWN
Requires-Dist: pandas
Requires-Dist: pyarrow
Requires-Dist: psycopg2-binary
Requires-Dist: sqlalchemy
Requires-Dist: jproperties
